yophonepy/__init__.py
yophonepy/async_bot.py
yophonepy/bot.py
yophonepy/models.py
yophonepy/murcap.py
yophonepy/utils.py
yophonepy-0.2.0.dist-info/licenses/LICENSE
yophonepy-0.2.0.dist-info/METADATA
yophonepy-0.2.0.dist-info/WHEEL
yophonepy-0.2.0.dist-info/top_level.txt
yophonepy-0.2.0.dist-info/RECORD
