Metadata-Version: 2.4
Name: yophonepy
Version: 0.2.0
Summary: A Python library for interacting with the YoPhone API.
Author-email: David Kocharyan <davidkocharyan94@gmail.com>
License-Expression: MIT
Project-URL: Homepage, https://github.com/david-kocharyan/yophonepy
Project-URL: Bug Tracker, https://github.com/david-kocharyan/yophonepy/issues
Requires-Python: >=3.7
License-File: LICENSE
Requires-Dist: requests
Requires-Dist: aiohttp
Requires-Dist: aiofiles
Dynamic: license-file
